README.txt
setup.py
lmfp33/__init__.py
lmfp33/db4.py
lmfp33/office.py
lmfp33/tool.py
lmfp33.egg-info/PKG-INFO
lmfp33.egg-info/SOURCES.txt
lmfp33.egg-info/dependency_links.txt
lmfp33.egg-info/requires.txt
lmfp33.egg-info/top_level.txt