Metadata-Version: 1.1
Name: lmfp33
Version: 1.0.0
Summary: 兰孟飞写的好用的包
Home-page: https://user.qzone.qq.com/865377886
Author: lanmengfei
Author-email: 865377886@qq.com
License: MIT
Platform: UNKNOWN
Classifier: Environment :: Web Environment
Classifier: Intended Audience :: Developers
Classifier: Operating System :: OS Independent
Classifier: Topic :: Text Processing :: Indexing
Classifier: Topic :: Utilities
Classifier: Topic :: Internet
Classifier: Topic :: Software Development :: Libraries :: Python Modules
Classifier: Programming Language :: Python
Classifier: Programming Language :: Python :: 3
